parquet_inspector/__init__.py
parquet_inspector/main.py
parquet_inspector-0.1.1.dist-info/entry_points.txt
parquet_inspector-0.1.1.dist-info/LICENSE
parquet_inspector-0.1.1.dist-info/WHEEL
parquet_inspector-0.1.1.dist-info/METADATA
parquet_inspector-0.1.1.dist-info/RECORD
