Metadata-Version: 2.1
Name: parquet-inspector
Version: 0.1.1
Summary: CLI tool for inspecting parquet files.
License: MIT
Author: Dominic Thorn
Author-email: dominic.thorn@gmail.com
Requires-Python: >=3.6.2,<4.0.0
Classifier: License :: OSI Approved :: MIT License
Classifier: Programming Language :: Python :: 3
Classifier: Programming Language :: Python :: 3.7
Classifier: Programming Language :: Python :: 3.8
Classifier: Programming Language :: Python :: 3.9
Classifier: Programming Language :: Python :: 3.10
Requires-Dist: pyarrow (>=6.0.0)
